{
  "name": "collections/blog/posts/7ccd9478ed73",
  "__resolveType": "blog/loaders/Blogpost.ts",
  "post": {
    "authors": [
      {
        "name": "Tiago Heineck",
        "email": "tiago.heineck@wavecommerce.com.br",
        "jobTitle": "Tiago Heineck, 22 anos, graduando em Publicidade e Propaganda pela UFRGS. Já trabalhei como copywriter e redator, tendo experiência em agências tradicionais e de marketing digital. Atualmente, trabalho com redação de conteúdo para SEO na Wave Commerce.",
        "company": "Wave Commerce",
        "avatar": "https://data.decoassets.com/site-wave/d674c4fe-d4eb-4b40-9adf-97f21915fe88/tiago.jpg"
      }
    ],
    "categories": [
      {
        "name": "E-commerce",
        "slug": "e-commerce"
      }
    ],
    "extraProps": [],
    "title": "VTEX Pick and Pack: A Solução Definitiva para Otimizar o Fulfillment no E-commerce",
    "date": "2024-11-19",
    "slug": "vtex-pick-and-pack",
    "excerpt": "Entenda o que é o VTEX Pick and Pack, como ele funciona e quais são os benefícios para o fulfillment do seu E-commerce.",
    "seo": {
      "description": "Entenda o que é o VTEX Pick and Pack, como ele funciona e quais são os benefícios para o fulfillment do seu E-commerce."
    },
    "image": "https://data.decoassets.com/site-wave/ca26fac8-3c36-4b4b-97f6-09344e64b393/vtex-pick-and-pack.webp",
    "content": "<p>No mundo do e-commerce, o gerenciamento eficiente do fulfillment é fundamental para garantir que os clientes recebam seus pedidos de maneira rápida e precisa. É aí que entra o VTEX Pick and Pack, uma solução inovadora da plataforma VTEX, que oferece ferramentas para otimizar a coleta, embalagem e entrega de pedidos. Neste artigo, você entenderá o que é o VTEX Pick and Pack, como ele funciona e quais são os benefícios para o seu negócio online.</p><h2>O Que É VTEX Pick and Pack?</h2><p>O VTEX Pick and Pack é uma ferramenta voltada para o <strong>gerenciamento integrado do processo de fulfillment</strong> em lojas virtuais. Ele permite que os e-commerces gerenciem a <strong>coleta, empacotamento e envio de pedidos de maneira ágil, centralizando essas etapas em um só lugar</strong>. A solução oferece visibilidade e controle total para os comerciantes, permitindo a execução de processos de forma rápida e eficiente.</p><h2>Por Que o VTEX Pick and Pack É Importante para o E-commerce?</h2><p>Em um ambiente tão competitivo como o e-commerce, cada minuto conta. O VTEX Pick and Pack permite que os comerciantes centralizem e automatizem tarefas essenciais, melhorando a precisão e a velocidade das operações. A agilidade no atendimento ao cliente, proporcionada pela solução, pode ser um diferencial para fidelizar clientes e fortalecer a reputação do negócio.</p><h3>Notificações para Entregadores</h3><p>Os <strong>entregadores</strong> responsáveis pela separação de pedidos recebem notificações automáticas para iniciar o processo de coleta, <strong>diretamente em seus dispositivos</strong>, sem precisar acessar o Admin da loja. Essa funcionalidade permite uma resposta mais rápida e reduz o risco de atrasos ou erros na coleta.</p><h3>Configuração e Impressão de Etiquetas</h3><p>Outra funcionalidade essencial é a configuração de pacotes e a impressão de etiquetas com códigos de barras. Esse recurso <strong>permite que o entregador faça a leitura dos códigos com segurança</strong>, evitando problemas de coleta e garantindo que o pedido certo chegue ao cliente.</p><h3>Comunicação com o Cliente</h3><p>Em cenários de substituição, recusa ou adição de itens, a comunicação entre o entregador e o cliente é essencial. Com o VTEX Pick and Pack, <strong>o entregador pode manter contato direto com o cliente</strong>, o que ajuda a resolver rapidamente possíveis problemas e garantir a satisfação do cliente.</p><h3>Gerenciamento da Agenda do Entregador</h3><p>O VTEX Pick and Pack também facilita o gerenciamento da agenda do entregador, com <strong>rastreamento em tempo real do pedido</strong>. Isso permite que os gestores de e-commerce monitorem cada etapa da entrega e se preparem para eventuais imprevistos, garantindo uma experiência de entrega tranquila para o cliente.</p><h3>Otimização de Rotas com Google Maps e Waze</h3><p>A ferramenta possui <strong>integração com o Google Maps e o Waze</strong>, otimizando as rotas de entrega. Esse recurso é especialmente útil para reduzir o tempo de deslocamento e assegurar que os entregadores sigam o caminho mais eficiente até o destino final.</p><h3>Comprovantes de Entrega</h3><p>Para maior segurança e controle, o VTEX Pick and Pack permite que os entregadores façam o <strong>upload de comprovantes de entrega, como assinaturas, fotos e observações do cliente</strong>. Isso fornece um registro detalhado do processo, essencial para casos de disputa ou confirmação de entrega.</p><p>Além disso, a VTEX anunciou um pacote com ainda mais funcionalidades para seu aplicativo, como Trabalho Offline, Regras de Separação, Localização de Produtos e Insights de Envio.</p><h2>VTEX Pick and Pack: Benefícios para o E-commerce</h2><p>O uso do VTEX Pick and Pack traz inúmeros benefícios para o e-commerce, incluindo: agilidade no fulfillment, redução de erros, maior precisão na coleta e empacotamento de pedidos, e melhoria na experiência do cliente. A seguir, veremos outros pontos importantes que tornam essa ferramenta indispensável.</p><h3>A Importância do Monitoramento em Tempo Real</h3><p>O monitoramento em tempo real é um dos grandes diferenciais do VTEX Pick and Pack. Com ele, os comerciantes conseguem acompanhar todo o fluxo de pedidos, permitindo intervenções rápidas em caso de problemas e melhorando a eficiência geral do fulfillment.</p><h3>Treinamento da Equipe e Interface Intuitiva</h3><p>A interface do VTEX Pick and Pack é <strong>intuitiva,</strong> <strong>facilitando a adoção e o uso pelos operadores</strong>. Ainda assim, o treinamento da equipe é recomendado para que todos estejam familiarizados com as funcionalidades e utilizem a ferramenta de forma eficaz.</p><h2>Integração Completa com a Plataforma VTEX</h2><p>A integração com a plataforma VTEX é um dos grandes diferenciais dessa solução. Ela permite centralizar operações de inventário, pedidos e fulfillment, o que facilita a coordenação entre departamentos e melhora a eficiência operacional.</p><h2>A Melhor Forma de Implementar VTEX Pick And Pack</h2><p>A Wave Commerce é uma agência de full commerce altamente especializada em E-commerce e performance digital, sendo reconhecida como <strong>a melhor agência de performance do Brasil pela ABComm.</strong></p><p>Como parceira oficial da VTEX, a Wave Commerce possui um entendimento profundo das funcionalidades e particularidades dessa plataforma, o que permite uma configuração do Pick and Pack alinhada às necessidades específicas de cada operação.</p><p>A agência oferece suporte completo desde a fase de planejamento até o acompanhamento pós-implementação, garantindo que o e-commerce obtenha o máximo da ferramenta, com uma operação de <a target=\"_blank\" rel=\"noopener noreferrer nofollow\" href=\"https://www.wavecommerce.com.br/fulfillment/\"><u><span>fulfillment</span></u></a> mais eficiente e uma experiência de entrega superior para os clientes.</p><p><strong>Entre em contato e junte-se à onda!</strong></p><h2>FAQs</h2><h3>Quais são as vantagens do VTEX Pick and Pack para o e-commerce?</h3><p>O VTEX Pick and Pack oferece agilidade no fulfillment, redução de erros, otimização de rotas, e permite um melhor monitoramento do processo de entrega. </p><h3>Como o VTEX Pick and Pack ajuda a melhorar a experiência do cliente? </h3><p>Ele possibilita a comunicação entre entregador e cliente e fornece atualizações em tempo real, o que contribui para uma experiência mais confiável e satisfatória. </p><h3>Quais ferramentas de navegação o VTEX Pick and Pack utiliza para rotas otimizadas? </h3><p>Ele integra o Google Maps e o Waze, facilitando o percurso do entregador até o cliente. </p><h3>A equipe precisa de treinamento para usar o VTEX Pick and Pack?</h3><p>Sim, apesar de ser intuitivo, um treinamento básico é recomendado para que a equipe aproveite ao máximo todas as funcionalidades.</p><h3>O VTEX Pick and Pack é compatível com outros sistemas de gestão de e-commerce? </h3><p>Sim, sua integração com a plataforma VTEX permite centralizar várias operações em um único sistema, facilitando a gestão completa do e-commerce. </p>"
  }
}
